request_id/__init__.py
request_id-1.0.1.dist-info/LICENSE.txt
request_id-1.0.1.dist-info/METADATA
request_id-1.0.1.dist-info/WHEEL
request_id-1.0.1.dist-info/entry_points.txt
request_id-1.0.1.dist-info/top_level.txt
request_id-1.0.1.dist-info/RECORD
